LICENSE
MANIFEST.in
README.rst
setup.py
django_pylibmc/__init__.py
django_pylibmc/memcached.py
django_pylibmc_sasl.egg-info/PKG-INFO
django_pylibmc_sasl.egg-info/SOURCES.txt
django_pylibmc_sasl.egg-info/dependency_links.txt
django_pylibmc_sasl.egg-info/not-zip-safe
django_pylibmc_sasl.egg-info/requires.txt
django_pylibmc_sasl.egg-info/top_level.txt