Metadata-Version: 1.0
Name: django-pylibmc-sasl
Version: 0.2.3
Summary: Django cache backend using pylibmc-sasl
Home-page: http://github.com/kennethreitz/django-pylibmc-sasl
Author: Jeff Balogh
Author-email: jbalogh@mozilla.com
License: BSD
Platform: UNKNOWN
Classifier: Development Status :: 4 - Beta
Classifier: Environment :: Web Environment
Classifier: Environment :: Web Environment :: Mozilla
Classifier: Framework :: Django
Classifier: Intended Audience :: Developers
Classifier: License :: OSI Approved :: BSD License
Classifier: Operating System :: OS Independent
Classifier: Programming Language :: Python
Classifier: Topic :: Software Development :: Libraries :: Python Modules
